LICENSE
MANIFEST.in
README
setup.cfg
setup.py
roro_ioc/__init__.py
roro_ioc/ast_injection.py
roro_ioc/container.py
roro_ioc/container_field_registry.py
roro_ioc/direct_injector.py
roro_ioc/exceptions.py
roro_ioc/factory_inspection.py
roro_ioc/inject.py
roro_ioc/injected_tag.py
roro_ioc/instance_ioc_container.py
roro_ioc.egg-info/PKG-INFO
roro_ioc.egg-info/SOURCES.txt
roro_ioc.egg-info/dependency_links.txt
roro_ioc.egg-info/requires.txt
roro_ioc.egg-info/top_level.txt