Metadata-Version: 1.0
Name: roro-ioc
Version: 0.1.11
Summary: IOC Injection for python
Home-page: https://github.com/twgOren/roroioc
Author: Twiggle
Author-email: oren@twiggle.com
License: UNKNOWN
Keywords: ioc
Platform: UNKNOWN
